mypulp/__init__.py
mypulp/__main__.py
mypulp/mypulp - Python Package Index.url
mypulp-0.0.12.dist-info/METADATA
mypulp-0.0.12.dist-info/WHEEL
mypulp-0.0.12.dist-info/RECORD
