Metadata-Version: 2.1
Name: mypulp
Version: 0.0.12
Summary: `mypulp` is a package for mypulp.
Home-page: https://github.com/SaitoTsutomu/mypulp
License: PSFL
Author: Mikio Kubo
Author-email: kubomikio@gmail.com
Requires-Python: >=3.11,<4.0
Classifier: Development Status :: 1 - Planning
Classifier: License :: OSI Approved :: Python Software Foundation License
Classifier: License :: Other/Proprietary License
Classifier: Programming Language :: Python
Classifier: Programming Language :: Python :: 3
Classifier: Programming Language :: Python :: 3.11
Classifier: Programming Language :: Python :: 3.12
Classifier: Topic :: Software Development
Requires-Dist: pulp (>=2.8,<3.0)
